vanilla_option_pricing/__init__.py
vanilla_option_pricing/calibration.py
vanilla_option_pricing/models.py
vanilla_option_pricing/option.py
vanilla_option_pricing/option_pricing.py
vanilla_option_pricing-0.1.0.dist-info/WHEEL
vanilla_option_pricing-0.1.0.dist-info/METADATA
vanilla_option_pricing-0.1.0.dist-info/RECORD
