Metadata-Version: 2.1
Name: vanilla-option-pricing
Version: 0.1.0
Summary: Stochastic model for vanilla option pricing
Home-page: https://github.com/donlelef/vanilla-option-pricing
License: MIT
Keywords: quantitative-finance,option-pricing,stochastic-models
Author: Emanuele Fabbiani
Author-email: donlelef@gmail.com
Requires-Python: >=3.7,<4.0
Classifier: Development Status :: 5 - Production/Stable
Classifier: Intended Audience :: Education
Classifier: Intended Audience :: Financial and Insurance Industry
Classifier: Intended Audience :: Science/Research
Classifier: License :: OSI Approved :: MIT License
Classifier: Operating System :: OS Independent
Classifier: Programming Language :: Python :: 3
Classifier: Programming Language :: Python :: 3.7
Classifier: Programming Language :: Python :: 3.8
Classifier: Topic :: Scientific/Engineering :: Mathematics
Requires-Dist: numpy (>=1.19.2,<2.0.0)
Requires-Dist: pandas (>=1.1.3,<2.0.0)
Requires-Dist: py-lets-be-rational (>=1.0.1,<2.0.0)
Requires-Dist: py_vollib (>=1.0.1,<2.0.0)
Requires-Dist: scipy (>=1.5.2,<2.0.0)
Project-URL: Documentation, https://vanilla-option-pricing.readthedocs.io
Project-URL: Repository, https://github.com/donlelef/vanilla-option-pricing
